markdown_toc_creator/__init__.py
markdown_toc_creator/create_toc.py
markdown_toc_creator/exceptions.py
markdown_toc_creator/main.py
markdown_toc_creator/toc_entry.py
markdown_toc_creator-0.1.1.dist-info/licenses/LICENSE
markdown_toc_creator-0.1.1.dist-info/METADATA
markdown_toc_creator-0.1.1.dist-info/WHEEL
markdown_toc_creator-0.1.1.dist-info/entry_points.txt
markdown_toc_creator-0.1.1.dist-info/top_level.txt
markdown_toc_creator-0.1.1.dist-info/RECORD
