Metadata-Version: 2.4
Name: markdown_toc_creator
Version: 0.1.1
Summary: Create table of contents for markdown files
License: MIT License
Project-URL: Homepage, https://github.com/jsh9/markdown-toc-creator
Classifier: License :: OSI Approved :: MIT License
Classifier: Programming Language :: Python :: 3
Classifier: Programming Language :: Python :: 3 :: Only
Requires-Python: >=3.10
License-File: LICENSE
Requires-Dist: click>=8.0.0
Requires-Dist: beautifulsoup4>=4.12.0
Dynamic: license-file
